{
    "current_feature": "F003-01-electricsql",
    "current_task_id": "T007-replace-use-sync-hook",
    "status": "completed",
    "tasks": [
        { "id": "T001-remove-server-sync-routes", "status": "completed", "attempts": 1, "errors": null },
        { "id": "T002-add-electric-docker-service", "status": "completed", "attempts": 1, "errors": null },
        { "id": "T003-electrify-postgres-tables", "status": "completed", "attempts": 1, "errors": null },
        { "id": "T004-remove-mobile-sync-services", "status": "completed", "attempts": 1, "errors": null },
        { "id": "T005-update-sync-types", "status": "completed", "attempts": 1, "errors": null },
        { "id": "T006-setup-electric-client", "status": "completed", "attempts": 1, "errors": null },
        { "id": "T007-replace-use-sync-hook", "status": "completed", "attempts": 1, "errors": null }
    ]
}
